pyturbo/__init__.py
pyturbo/aero/__init__.py
pyturbo/aero/airfoil2D.py
pyturbo/aero/airfoil3D.py
pyturbo/aero/airfoil_wavy.py
pyturbo/aero/centrif.py
pyturbo/aero/passage2D.py
pyturbo/helper/__init__.py
pyturbo/helper/arc.py
pyturbo/helper/bezier.py
pyturbo/helper/bisect.py
pyturbo/helper/centrif_comp_domain.py
pyturbo/helper/centrif_passage.py
pyturbo/helper/centroid.py
pyturbo/helper/convert_to_ndarray.py
pyturbo/helper/csapi.py
pyturbo/helper/derivative.py
pyturbo/helper/dist.py
pyturbo/helper/ellispe.py
pyturbo/helper/exp_ratio.py
pyturbo/helper/fit_eta_tt.json
pyturbo/helper/hermite.py
pyturbo/helper/interparc.py
pyturbo/helper/line2D.py
pyturbo/helper/min_max_check.py
pyturbo/helper/order_pts.py
pyturbo/helper/pspline.py
pyturbo/helper/ray.py
pyturbo/helper/resample.py
pyturbo/helper/rotate_array_values.py
pyturbo/helper/stacking.py
pyturbo/helper/unique_xy.py
pyturbo/helper/wave.py
pyturbo/helper/xr_mprime.py
pyturbo/ml/gramian_angular_field.py
pyturbo/wiki/2D_design/2D_airfoil.png
pyturbo/wiki/2D_design/Deriv_2.png
pyturbo/wiki/2D_design/camber_line.png
pyturbo/wiki/2D_design/s_c.png
pyturbo/wiki/3D_design/stator3D_shell.png
pyturbo/wiki/3D_design/stator3D_wavy_const_te_radius.PNG
pyturbo/wiki/3D_design/stator3D_wavy_variable_te_radius.PNG
pyturbo/wiki/3D_design/stator3D_whisker.PNG
pyturbo/wiki/3D_design/stator_3D.png
pyturbo/wiki/HeatPipe/circle_cross_section.png
pyturbo/wiki/HeatPipe/pathline_close_loop_no_return.png
pyturbo/wiki/HeatPipe/pathline_close_loop_return.png
pyturbo/wiki/HeatPipe/pathline_periodic_loop.png
pyturbo/wiki/HeatPipe/pattern_close_loop_no_return.PNG
pyturbo/wiki/HeatPipe/pattern_close_loop_return.PNG
pyturbo/wiki/HeatPipe/periodic_loop.PNG
pyturbo/wiki/HeatPipe/rectangle_cross_section.png
pyturbo/wiki/HeatPipe/rectangle_cross_section_fillet.png
pyturbo_aero-1.2.5.dist-info/METADATA
pyturbo_aero-1.2.5.dist-info/WHEEL
pyturbo_aero-1.2.5.dist-info/RECORD
