Metadata-Version: 2.1
Name: pyturbo-aero
Version: 1.2.5
Summary: PyTurbo_Aero is a Turbomachinery blade design library that lets you create a full 3D blades and passages.
Author: Paht Juangphanich
Author-email: paht.juangphanich@nasa.gov
Requires-Python: >=3.10
Classifier: Programming Language :: Python :: 3
Classifier: Programming Language :: Python :: 3.10
Classifier: Programming Language :: Python :: 3.11
Classifier: Programming Language :: Python :: 3.12
Requires-Dist: geomdl
Requires-Dist: matplotlib
Requires-Dist: numpy (>=1.80)
Requires-Dist: numpy-stl
Requires-Dist: pandas
Requires-Dist: plot3d
Requires-Dist: plotly
Requires-Dist: scipy
Requires-Dist: tqdm
